locallab_client/__init__.py
locallab_client/client.py
locallab_client/sync_client.py
locallab_client-1.1.0.dist-info/METADATA
locallab_client-1.1.0.dist-info/WHEEL
locallab_client-1.1.0.dist-info/top_level.txt
locallab_client-1.1.0.dist-info/RECORD
