Metadata-Version: 2.4
Name: locallab-client
Version: 1.1.0
Summary: Python client for LocalLab - A local LLM server
Home-page: https://github.com/UtkarshTheDev/LocalLab
Author: Utkarsh
Author-email: Utkarsh <utkarshweb2023@gmail.com>
License: MIT
Project-URL: Homepage, https://github.com/UtkarshTheDev/LocalLab
Project-URL: Documentation, https://github.com/UtkarshTheDev/LocalLab/tree/main/docs
Project-URL: Repository, https://github.com/UtkarshTheDev/LocalLab.git
Classifier: Development Status :: 5 - Production/Stable
Classifier: Intended Audience :: Developers
Classifier: License :: OSI Approved :: MIT License
Classifier: Operating System :: OS Independent
Classifier: Programming Language :: Python :: 3
Classifier: Programming Language :: Python :: 3.7
Classifier: Programming Language :: Python :: 3.8
Classifier: Programming Language :: Python :: 3.9
Classifier: Programming Language :: Python :: 3.10
Classifier: Programming Language :: Python :: 3.11
Requires-Python: >=3.7
Requires-Dist: aiohttp>=3.8.0
Requires-Dist: websockets>=10.0
Requires-Dist: pydantic>=2.0.0
Requires-Dist: asyncio>=3.4.3
Requires-Dist: nest-asyncio>=1.5.1
Dynamic: author
Dynamic: home-page
Dynamic: requires-python
